[
  {
    "title": "Handpicked Adventures",
    "description": "We search more than 700 destinations to bring you the best adventures tailored just for you."
  },
  {
    "title": "Exclusive Deals",
    "description": "From local gems to highlights, discover exclusive deals that make your travel dreams a reality."
  },
  {
    "title": "Trips That Match Your Request",
    "description": "Explore trips that match your request, featuring local gems and highlights that cater to your interests."
  }
]